ghkit/__init__.py
ghkit/cache/__init__.py
ghkit/cache/base.py
ghkit/cache/memory_cache.py
ghkit/cache/redis_cache.py
ghkit/database/__init__.py
ghkit/database/mysql_client.py
ghkit/database/redis_client.py
ghkit/enum/__init__.py
ghkit/fastapi/__init__.py
ghkit/fastapi/error.py
ghkit/fastapi/filter.py
ghkit/fastapi/paginate.py
ghkit/log/__init__.py
ghkit/messenger/__init__.py
ghkit/messenger/error.py
ghkit/messenger/mailer.py
ghkit/messenger/dingtalk/__init__.py
ghkit/messenger/dingtalk/customer_bot.py
ghkit/messenger/dingtalk/dingtalk.py
ghkit/messenger/dingtalk/message.py
ghkit/messenger/feishu/__init__.py
ghkit/messenger/feishu/app_bot.py
ghkit/messenger/feishu/custom_bot.py
ghkit/messenger/feishu/feishu.py
ghkit/messenger/feishu/message.py
ghkit-0.0.6.dist-info/METADATA
ghkit-0.0.6.dist-info/WHEEL
ghkit-0.0.6.dist-info/licenses/LICENSE
ghkit-0.0.6.dist-info/RECORD
