Metadata-Version: 2.4
Name: ghkit
Version: 0.0.6
Summary: Grand Honor Kit - 一个 Python 项目通用工具包，提供缓存、数据库、日志、消息通知等功能
Author-email: xingxing <chenxingyu@ndnu.edu.cn>
License: MIT
License-File: LICENSE
Keywords: cache,database,fastapi,logging,messenger,toolkit
Classifier: License :: OSI Approved :: MIT License
Classifier: Operating System :: OS Independent
Classifier: Programming Language :: Python :: 3
Classifier: Programming Language :: Python :: 3.10
Classifier: Programming Language :: Python :: 3.11
Classifier: Programming Language :: Python :: 3.12
Requires-Python: >=3.10
Requires-Dist: dbutils>=3.1.2
Requires-Dist: fastapi>=0.121.1
Requires-Dist: httpx>=0.28.1
Requires-Dist: loguru>=0.7.3
Requires-Dist: pydantic>=2.12.4
Requires-Dist: pymysql>=1.1.2
Requires-Dist: redis>=7.0.1
Requires-Dist: requests>=2.32.5
Requires-Dist: tortoise-orm>=0.25.1
Provides-Extra: demo
Requires-Dist: python-dotenv>=0.19.0; extra == 'demo'
Requires-Dist: uvicorn>=0.15.0; extra == 'demo'
Provides-Extra: dev
Requires-Dist: pre-commit>=4.4.0; extra == 'dev'
Provides-Extra: test
Requires-Dist: pytest-asyncio>=0.23.3; extra == 'test'
Requires-Dist: pytest-cov>=7.0.0; extra == 'test'
Requires-Dist: pytest>=9.0.0; extra == 'test'
